{
  "network": "nile",
  "chainId": "3",
  "deployedAt": "2025-07-29T05:52:28.895Z",
  "deployer": "TPUiCeNRjjEpo1NFJ1ZURfU1ziNNMtn8yu",
  "contracts": {
    "TronEscrowFactory": {
      "address": "TByM1nxjJsgZuh9SeEniex2Sa9iKNfu4hD",
      "txHash": "edfd804355f1ae71a1a02c4a82287076a00da874a82b5f193ab88326f0bd079b",
      "deploymentBlock": 59122379
    }
  },
  "configuration": {
    "finalityBlocks": "12",
    "minCancelDelay": "1800",
    "minSafetyDeposit": "1000000",
    "revealDelay": "60"
  }
}